m_n_kappa/__init__.py
m_n_kappa/crosssection.py
m_n_kappa/curvature_boundaries.py
m_n_kappa/curves_m_kappa.py
m_n_kappa/curves_m_n_kappa.py
m_n_kappa/deformation.py
m_n_kappa/function.py
m_n_kappa/general.py
m_n_kappa/geometry.py
m_n_kappa/loading.py
m_n_kappa/log.py
m_n_kappa/logging-config.yaml
m_n_kappa/material.py
m_n_kappa/points.py
m_n_kappa/section.py
m_n_kappa/shearconnector.py
m_n_kappa/solver.py
m_n_kappa/width.py
m_n_kappa-0.0.1.dist-info/METADATA
m_n_kappa-0.0.1.dist-info/WHEEL
m_n_kappa-0.0.1.dist-info/licenses/LICENSE
m_n_kappa-0.0.1.dist-info/RECORD
