Metadata-Version: 2.1
Name: m_n_kappa
Version: 0.0.1
Summary:     Open source library for using the strain-based method to compute
Project-URL: Homepage, https://github.com/JohannesSchorr/M-N-Kappa
Project-URL: Documentation, https://johannesschorr.github.io/M-N-Kappa/
Project-URL: Issue tracker, https://github.com/JohannesSchorr/M-N-Kappa/issues
Author-email: Johannes Schorr <johannes.schorr@gmail.com>
License-File: LICENSE
Keywords: beam,deformation,engineering,moment-curvature,multi-linear material,non-linear material,strain-based,structural-engineering
Classifier: License :: OSI Approved :: BSD License
Classifier: Natural Language :: English
Classifier: Operating System :: OS Independent
Classifier: Programming Language :: Python :: 3
Classifier: Programming Language :: Python :: 3.11
Classifier: Topic :: Education
Classifier: Topic :: Scientific/Engineering
Classifier: Typing :: Typed
Requires-Python: >=3.11
